MANIFEST.in
README.rst
setup.py
flatly/__init__.py
flatly.egg-info/PKG-INFO
flatly.egg-info/SOURCES.txt
flatly.egg-info/dependency_links.txt
flatly.egg-info/entry_points.txt
flatly.egg-info/requires.txt
flatly.egg-info/top_level.txt
flatly/flatly/+package+.py
flatly/flatly/README.rst_tmpl
flatly/flatly/development.ini_tmpl
flatly/flatly/setup.py_tmpl