Metadata-Version: 1.0
Name: flatly
Version: 0.2
Summary: Pyramid scaffold that is flat.  Kind of like Flask.
Home-page: http://github.com/ralphbean/flatly/
Author: Ralph Bean
Author-email: rbean@redhat.com
License: BSD
Keywords: pyramid
Platform: UNKNOWN
